setup.py
tempestas/__init__.py
tempestas/tempestas.py
tempestas.egg-info/PKG-INFO
tempestas.egg-info/SOURCES.txt
tempestas.egg-info/dependency_links.txt
tempestas.egg-info/requires.txt
tempestas.egg-info/top_level.txt