Metadata-Version: 1.0
Name: tempestas
Version: 2.0.1
Summary: Forecast data for the next 24 hours
Home-page: UNKNOWN
Author: UNKNOWN
Author-email: UNKNOWN
License: MIT
Keywords: weather,forecast,temperature
Platform: UNKNOWN
